main.py
java-stubs/__init__.pyi
java-stubs/applet/__init__.pyi
java-stubs/awt/__init__.pyi
java-stubs/awt/color/__init__.pyi
java-stubs/awt/datatransfer/__init__.pyi
java-stubs/awt/desktop/__init__.pyi
java-stubs/awt/dnd/__init__.pyi
java-stubs/awt/dnd/peer/__init__.pyi
java-stubs/awt/event/__init__.pyi
java-stubs/awt/font/__init__.pyi
java-stubs/awt/geom/__init__.pyi
java-stubs/awt/im/__init__.pyi
java-stubs/awt/im/spi/__init__.pyi
java-stubs/awt/image/__init__.pyi
java-stubs/awt/image/renderable/__init__.pyi
java-stubs/awt/peer/__init__.pyi
java-stubs/awt/print_/__init__.pyi
java-stubs/beans/__init__.pyi
java-stubs/beans/beancontext/__init__.pyi
java-stubs/io/__init__.pyi
java-stubs/lang/__init__.pyi
java-stubs/lang/annotation/__init__.pyi
java-stubs/lang/classfile/__init__.pyi
java-stubs/lang/classfile/attribute/__init__.pyi
java-stubs/lang/classfile/constantpool/__init__.pyi
java-stubs/lang/classfile/instruction/__init__.pyi
java-stubs/lang/constant/__init__.pyi
java-stubs/lang/foreign/__init__.pyi
java-stubs/lang/instrument/__init__.pyi
java-stubs/lang/invoke/__init__.pyi
java-stubs/lang/management/__init__.pyi
java-stubs/lang/module/__init__.pyi
java-stubs/lang/ref/__init__.pyi
java-stubs/lang/reflect/__init__.pyi
java-stubs/lang/runtime/__init__.pyi
java-stubs/math/__init__.pyi
java-stubs/net/__init__.pyi
java-stubs/net/http/__init__.pyi
java-stubs/net/spi/__init__.pyi
java-stubs/nio/__init__.pyi
java-stubs/nio/channels/__init__.pyi
java-stubs/nio/channels/spi/__init__.pyi
java-stubs/nio/charset/__init__.pyi
java-stubs/nio/charset/spi/__init__.pyi
java-stubs/nio/file/__init__.pyi
java-stubs/nio/file/attribute/__init__.pyi
java-stubs/nio/file/spi/__init__.pyi
java-stubs/rmi/__init__.pyi
java-stubs/rmi/dgc/__init__.pyi
java-stubs/rmi/registry/__init__.pyi
java-stubs/rmi/server/__init__.pyi
java-stubs/security/__init__.pyi
java-stubs/security/cert/__init__.pyi
java-stubs/security/interfaces/__init__.pyi
java-stubs/security/spec/__init__.pyi
java_stubs_converted_strings-0.1.0.dist-info/METADATA
java_stubs_converted_strings-0.1.0.dist-info/WHEEL
java_stubs_converted_strings-0.1.0.dist-info/top_level.txt
java_stubs_converted_strings-0.1.0.dist-info/RECORD
