Metadata-Version: 2.4
Name: java-stubs-converted-strings
Version: 0.1.0
Summary: The JPype java.* type definitions with automatic Java string -> Python string conversions enabled
License-Expression: MIT
Project-URL: Repository, https://github.com/jstasiak/jpype-stubs
Project-URL: Bug Tracker, https://github.com/jstasiak/jpype-stubs/issues
Requires-Python: >=3.11
Requires-Dist: jpype1>=1.6.0
